terminalImgViewer/__init__.py
terminalImgViewer/lib.py
terminalImgViewer-0.0.9.dist-info/METADATA
terminalImgViewer-0.0.9.dist-info/WHEEL
terminalImgViewer-0.0.9.dist-info/top_level.txt
terminalImgViewer-0.0.9.dist-info/RECORD
